GoldenFace/__init__.py
GoldenFace/api.py
GoldenFace/example.py
GoldenFace/functions.py
GoldenFace/goldenFace.json
GoldenFace/goldenMath.py
GoldenFace/landmark.py
GoldenFace/landmark.yaml
GoldenFace/null.py
GoldenFace-1.1.data/scripts/ryb
GoldenFace-1.1.dist-info/LICENSE
GoldenFace-1.1.dist-info/METADATA
GoldenFace-1.1.dist-info/WHEEL
GoldenFace-1.1.dist-info/top_level.txt
GoldenFace-1.1.dist-info/RECORD
