Metadata-Version: 2.1
Name: GoldenFace
Version: 1.1
Summary: Facial Cosine Similarity,Face Golden Ratio Calculation And Facial Landmark Detecting/Drawing Library 
Home-page: https://github.com/Aksoylu/GoldenFace
Author: Umit Aksoylu
Author-email: umit@aksoylu.space
License: UNKNOWN
Platform: UNKNOWN
Classifier: Programming Language :: Python :: 3
Classifier: License :: OSI Approved :: MIT License
Classifier: Operating System :: OS Independent
